{
    "Body":"My phone was stolen 3 days ago and I found out who had it. I talked him into bringing it back. He did bring it but he had already did a master reset. Can I somehow retrieve my contacts",
    "ViewCount":"9",
    "LastActivityDate":"2015-08-13T05:54:53.687",
    "ClosedDate":"2015-08-13T13:58:29.483",
    "Title":"Recovering contacts from a device that has been reset",
    "LastEditorUserId":null,
    "Tags":"",
    "LastEditDate":null,
    "CommentCount":"1",
    "AnswerCount":"0",
    "AcceptedAnswerId":null,
    "Score":"0",
    "CommunityOwnedDate":null,
    "LastEditorDisplayName":null,
    "PostTypeId":"1",
    "OwnerUserId":"121971",
    "CreationDate":"2015-08-13T05:54:53.687",
    "FavoriteCount":null,
    "Id":"119114",
    "history":[
        {
            "Comment":null,
            "CreationDate":"2015-08-13T05:54:53.687",
            "UserDisplayName":null,
            "RevisionGUID":"4f64fefc-8c59-45d5-8e59-a1f314684f24",
            "UserId":"121971",
            "CloseReasonId":null,
            "PostId":"119114",
            "PostHistoryTypeId":"2",
            "Id":"390114",
            "Text":"My phone was stolen 3 days ago and I found out who had it. I talked him into bringing it back. He did bring it but he had already did a master reset. Can I somehow retrieve my contacts"
        },
        {
            "Comment":null,
            "CreationDate":"2015-08-13T05:54:53.687",
            "UserDisplayName":null,
            "RevisionGUID":"4f64fefc-8c59-45d5-8e59-a1f314684f24",
            "UserId":"121971",
            "CloseReasonId":null,
            "PostId":"119114",
            "PostHistoryTypeId":"1",
            "Id":"390115",
            "Text":"Recovering contacts from a device that has been reset"
        },
        {
            "Comment":null,
            "CreationDate":"2015-08-13T05:54:53.687",
            "UserDisplayName":null,
            "RevisionGUID":"4f64fefc-8c59-45d5-8e59-a1f314684f24",
            "UserId":"121971",
            "CloseReasonId":null,
            "PostId":"119114",
            "PostHistoryTypeId":"3",
            "Id":"390116",
            "Text":""
        },
        {
            "Comment":"101",
            "CreationDate":"2015-08-13T13:58:29.483",
            "UserDisplayName":null,
            "RevisionGUID":"64020d1d-726c-4c22-9d04-de0b32d4c458",
            "UserId":"981",
            "CloseReasonId":null,
            "PostId":"119114",
            "PostHistoryTypeId":"10",
            "Id":"390263",
            "Text":"{\"OriginalQuestionIds\":[89777],\"Voters\":[{\"Id\":981,\"DisplayName\":\"eldarerathis\"}]}"
        }
    ]
}