{
    "Body":"  Possible Duplicate:  How do I backup and restore SMS Messages?  Is it possible to move\/backup txt\/sms message from my phone to my PC?  I have Android 2.2  If this could be done via a usb cable, that would be ideal.",
    "ViewCount":"4103",
    "LastActivityDate":"2012-02-10T04:31:10.913",
    "ClosedDate":"2012-02-10T17:45:33.753",
    "Title":"Save txt messages to PC?",
    "LastEditorUserId":"267",
    "Tags":"",
    "LastEditDate":"2011-10-28T12:41:40.160",
    "CommentCount":"0",
    "AnswerCount":"1",
    "AcceptedAnswerId":"15067",
    "Score":"0",
    "CommunityOwnedDate":null,
    "LastEditorDisplayName":null,
    "PostTypeId":"1",
    "OwnerUserId":"2688",
    "CreationDate":"2011-10-28T08:53:41.507",
    "FavoriteCount":null,
    "Id":"15065",
    "history":[
        {
            "Comment":null,
            "CreationDate":"2011-10-28T08:53:41.507",
            "UserDisplayName":null,
            "RevisionGUID":"bb35624b-af8b-41fd-925b-6d4dd46af09b",
            "UserId":"2688",
            "CloseReasonId":null,
            "PostId":"15065",
            "PostHistoryTypeId":"2",
            "Id":"40289",
            "Text":"Is it possible to move\/backup txt\/sms message from my phone to my PC?  I have Android 2.2  If this could be done via a usb cable, that would be ideal."
        },
        {
            "Comment":null,
            "CreationDate":"2011-10-28T08:53:41.507",
            "UserDisplayName":null,
            "RevisionGUID":"bb35624b-af8b-41fd-925b-6d4dd46af09b",
            "UserId":"2688",
            "CloseReasonId":null,
            "PostId":"15065",
            "PostHistoryTypeId":"1",
            "Id":"40290",
            "Text":"Save txt messages to PC?"
        },
        {
            "Comment":null,
            "CreationDate":"2011-10-28T08:53:41.507",
            "UserDisplayName":null,
            "RevisionGUID":"bb35624b-af8b-41fd-925b-6d4dd46af09b",
            "UserId":"2688",
            "CloseReasonId":null,
            "PostId":"15065",
            "PostHistoryTypeId":"3",
            "Id":"40291",
            "Text":""
        },
        {
            "Comment":"edited tags",
            "CreationDate":"2011-10-28T12:41:40.160",
            "UserDisplayName":null,
            "RevisionGUID":"60794a91-bc55-4ab8-917a-5f4fd9d97439",
            "UserId":"267",
            "CloseReasonId":null,
            "PostId":"15065",
            "PostHistoryTypeId":"6",
            "Id":"40303",
            "Text":""
        },
        {
            "Comment":"insert duplicate link",
            "CreationDate":"2012-02-10T17:45:36.093",
            "UserDisplayName":null,
            "RevisionGUID":"c42fdd8d-3daa-46c0-af9e-f8a39c6be34b",
            "UserId":"-1",
            "CloseReasonId":null,
            "PostId":"15065",
            "PostHistoryTypeId":"5",
            "Id":"53504",
            "Text":"> **Possible Duplicate:**  > [How do I backup and restore SMS Messages?](http:\/\/android.stackexchange.com\/questions\/2466\/how-do-i-backup-and-restore-sms-messages)  Is it possible to move\/backup txt\/sms message from my phone to my PC?  I have Android 2.2  If this could be done via a usb cable, that would be ideal."
        },
        {
            "Comment":"1",
            "CreationDate":"2012-02-10T17:45:33.753",
            "UserDisplayName":null,
            "RevisionGUID":"9f1e9275-5fe7-45aa-ac71-976b18f7909c",
            "UserId":"1465",
            "CloseReasonId":null,
            "PostId":"15065",
            "PostHistoryTypeId":"10",
            "Id":"53505",
            "Text":"{\"OriginalQuestionIds\":[2466],\"Voters\":[{\"Id\":1465,\"DisplayName\":\"Matthew Read\"}]}"
        }
    ]
}