{
    "Body":"  Possible Duplicate:  Do task killers actually work?  I was just going through this article on Lifehacker. Do these kind of apps really help in performance, or do they create more problems?",
    "ViewCount":"34",
    "LastActivityDate":"2013-11-13T07:24:56.693",
    "ClosedDate":"2013-01-22T14:40:21.790",
    "Title":"Are Memory Cleanup Apps for Android Good or Bad?",
    "LastEditorUserId":"5342",
    "Tags":"",
    "LastEditDate":"2013-11-13T07:24:56.693",
    "CommentCount":"3",
    "AnswerCount":"0",
    "AcceptedAnswerId":null,
    "Score":"0",
    "CommunityOwnedDate":null,
    "LastEditorDisplayName":null,
    "PostTypeId":"1",
    "OwnerUserId":"27158",
    "CreationDate":"2013-01-22T14:06:51.657",
    "FavoriteCount":null,
    "Id":"38146",
    "history":[
        {
            "Comment":null,
            "CreationDate":"2013-01-22T14:06:51.657",
            "UserDisplayName":null,
            "RevisionGUID":"ab2c1be2-b8e0-4f27-80d5-dec35dd04bac",
            "UserId":"27158",
            "CloseReasonId":null,
            "PostId":"38146",
            "PostHistoryTypeId":"2",
            "Id":"116503",
            "Text":"I was just going through this article on Lifehacker. Do these kind of apps really help in performance or they create more problems?    http:\/\/lifehacker.com\/5650894\/android-task-killers-explained-what-they-do-and-why-you-shouldnt-use-them"
        },
        {
            "Comment":null,
            "CreationDate":"2013-01-22T14:06:51.657",
            "UserDisplayName":null,
            "RevisionGUID":"ab2c1be2-b8e0-4f27-80d5-dec35dd04bac",
            "UserId":"27158",
            "CloseReasonId":null,
            "PostId":"38146",
            "PostHistoryTypeId":"1",
            "Id":"116504",
            "Text":"Memory Cleanup Apps for Andriod - Good or Bad"
        },
        {
            "Comment":null,
            "CreationDate":"2013-01-22T14:06:51.657",
            "UserDisplayName":null,
            "RevisionGUID":"ab2c1be2-b8e0-4f27-80d5-dec35dd04bac",
            "UserId":"27158",
            "CloseReasonId":null,
            "PostId":"38146",
            "PostHistoryTypeId":"3",
            "Id":"116505",
            "Text":""
        },
        {
            "Comment":"Linkified Lifehacker",
            "CreationDate":"2013-01-22T14:18:34.087",
            "UserDisplayName":null,
            "RevisionGUID":"990826cb-dabb-4988-813c-1de9ab5e52be",
            "UserId":"4003",
            "CloseReasonId":null,
            "PostId":"38146",
            "PostHistoryTypeId":"5",
            "Id":"116508",
            "Text":"I was just going through this article on [Lifehacker](http:\/\/lifehacker.com\/5650894\/android-task-killers-explained-what-they-do-and-why-you-shouldnt-use-them). Do these kind of apps really help in performance or they create more problems?"
        },
        {
            "Comment":"insert duplicate link",
            "CreationDate":"2013-01-22T14:40:21.790",
            "UserDisplayName":null,
            "RevisionGUID":"09ad6c0c-82a6-4e82-90b2-c490b12b6f55",
            "UserId":"-1",
            "CloseReasonId":null,
            "PostId":"38146",
            "PostHistoryTypeId":"5",
            "Id":"116519",
            "Text":"> **Possible Duplicate:**  > [Do task killers actually work?](http:\/\/android.stackexchange.com\/questions\/18765\/do-task-killers-actually-work)  I was just going through this article on [Lifehacker](http:\/\/lifehacker.com\/5650894\/android-task-killers-explained-what-they-do-and-why-you-shouldnt-use-them). Do these kind of apps really help in performance or they create more problems?"
        },
        {
            "Comment":"1",
            "CreationDate":"2013-01-22T14:40:21.790",
            "UserDisplayName":null,
            "RevisionGUID":"9dd4f668-ec17-4a54-b23a-d9b91b8e517e",
            "UserId":"10",
            "CloseReasonId":null,
            "PostId":"38146",
            "PostHistoryTypeId":"10",
            "Id":"116520",
            "Text":"{\"OriginalQuestionIds\":[18765],\"Voters\":[{\"Id\":4003,\"DisplayName\":\"t0mm13b\"},{\"Id\":10,\"DisplayName\":\"Bryan Denny\"}]}"
        },
        {
            "Comment":"edited tags",
            "CreationDate":"2013-01-22T20:36:22.440",
            "UserDisplayName":null,
            "RevisionGUID":"361fca80-ff64-482b-956e-4d4f4e0f4548",
            "UserId":"267",
            "CloseReasonId":null,
            "PostId":"38146",
            "PostHistoryTypeId":"6",
            "Id":"116594",
            "Text":""
        },
        {
            "Comment":"rephrase",
            "CreationDate":"2013-11-13T07:24:56.693",
            "UserDisplayName":null,
            "RevisionGUID":"674ef9ad-2399-419f-b85e-086ed138bfc0",
            "UserId":"5342",
            "CloseReasonId":null,
            "PostId":"38146",
            "PostHistoryTypeId":"5",
            "Id":"190728",
            "Text":"> **Possible Duplicate:**  > [Do task killers actually work?](http:\/\/android.stackexchange.com\/questions\/18765\/do-task-killers-actually-work)  I was just going through this article on [Lifehacker](http:\/\/lifehacker.com\/5650894\/android-task-killers-explained-what-they-do-and-why-you-shouldnt-use-them). Do these kind of apps really help in performance, or do they create more problems?"
        },
        {
            "Comment":"rephrase",
            "CreationDate":"2013-11-13T07:24:56.693",
            "UserDisplayName":null,
            "RevisionGUID":"674ef9ad-2399-419f-b85e-086ed138bfc0",
            "UserId":"5342",
            "CloseReasonId":null,
            "PostId":"38146",
            "PostHistoryTypeId":"4",
            "Id":"190729",
            "Text":"Are Memory Cleanup Apps for Android Good or Bad?"
        }
    ]
}