{
    "Body":"I have Locked myself out of my phone because I entered too many pattern attempts. I can't sign into my Google account because my wi-fi isn't turned on. So I need to factory reset it. I'm just wondering what will I lose. My photos and videos are saved onto my phone, will I lose them?If there are any other options in getting back into my without factory resetting it, it would be greatly appreciated.ThanksBy the way I have a Samsung Galaxy Xcover",
    "ViewCount":"75483",
    "LastActivityDate":"2013-06-01T21:31:05.953",
    "ClosedDate":"2013-06-02T03:24:22.340",
    "Title":"What will I lose when I do a factory reset?",
    "LastEditorUserId":"35087",
    "Tags":"",
    "LastEditDate":"2013-06-01T21:31:05.953",
    "CommentCount":"5",
    "AnswerCount":"1",
    "AcceptedAnswerId":"46484",
    "Score":"2",
    "CommunityOwnedDate":null,
    "LastEditorDisplayName":null,
    "PostTypeId":"1",
    "OwnerUserId":"35087",
    "CreationDate":"2013-06-01T20:10:46.957",
    "FavoriteCount":"0",
    "Id":"46482",
    "history":[
        {
            "Comment":null,
            "CreationDate":"2013-06-01T20:10:46.957",
            "UserDisplayName":null,
            "RevisionGUID":"bb4f0b68-72a0-47a4-92df-5ac91223d704",
            "UserId":"35087",
            "CloseReasonId":null,
            "PostId":"46482",
            "PostHistoryTypeId":"2",
            "Id":"150244",
            "Text":"I have Locked myself out of my phone because I entered too many pattern attempts. I can't sign into my Google account because my wi-fi is turned on. So I need to factory reset it. I'm just wondering what will I lose. My photos and videos are saved onto my phone, will I lose them?If there are any other options in getting back into my without factory resetting it, it would be greatly appreciated.ThanksBy the way I have a Samsung Galaxy Xcover"
        },
        {
            "Comment":null,
            "CreationDate":"2013-06-01T20:10:46.957",
            "UserDisplayName":null,
            "RevisionGUID":"bb4f0b68-72a0-47a4-92df-5ac91223d704",
            "UserId":"35087",
            "CloseReasonId":null,
            "PostId":"46482",
            "PostHistoryTypeId":"1",
            "Id":"150245",
            "Text":"What will I lose when I do a factory reset?"
        },
        {
            "Comment":null,
            "CreationDate":"2013-06-01T20:10:46.957",
            "UserDisplayName":null,
            "RevisionGUID":"bb4f0b68-72a0-47a4-92df-5ac91223d704",
            "UserId":"35087",
            "CloseReasonId":null,
            "PostId":"46482",
            "PostHistoryTypeId":"3",
            "Id":"150246",
            "Text":""
        },
        {
            "Comment":"added 3 characters in body",
            "CreationDate":"2013-06-01T21:31:05.953",
            "UserDisplayName":null,
            "RevisionGUID":"574be976-5013-4646-9aa0-910717f6509c",
            "UserId":"35087",
            "CloseReasonId":null,
            "PostId":"46482",
            "PostHistoryTypeId":"5",
            "Id":"150261",
            "Text":"I have Locked myself out of my phone because I entered too many pattern attempts. I can't sign into my Google account because my wi-fi isn't turned on. So I need to factory reset it. I'm just wondering what will I lose. My photos and videos are saved onto my phone, will I lose them?If there are any other options in getting back into my without factory resetting it, it would be greatly appreciated.ThanksBy the way I have a Samsung Galaxy Xcover"
        },
        {
            "Comment":"1",
            "CreationDate":"2013-06-02T03:24:22.340",
            "UserDisplayName":null,
            "RevisionGUID":"3ba428d8-ff82-424b-b419-9a5e9ee20d1f",
            "UserId":"-1",
            "CloseReasonId":null,
            "PostId":"46482",
            "PostHistoryTypeId":"10",
            "Id":"150295",
            "Text":"{\"OriginalQuestionIds\":[18029,35847],\"Voters\":[{\"Id\":267,\"DisplayName\":\"Al Everett\"},{\"Id\":16575,\"DisplayName\":\"Izzy\"},{\"Id\":4003,\"DisplayName\":\"t0mm13b\"},{\"Id\":5342,\"DisplayName\":\"geffchang\"},{\"Id\":8197,\"DisplayName\":\"roxan\"}]}"
        }
    ]
}